{
  "type": "minecraft:chest",
  "pools": [
    {
      "name": "main",
      "rolls": {
        "min": 0.0,
        "max": 2.0,
        "type": "minecraft:uniform"
      },
      "entries": [
        {
          "type": "minecraft:item",
          "weight": 5,
          "name": "vampirism:item_garlic"
        },
        {
          "type": "minecraft:item",
          "weight": 5,
          "functions": [
            {
              "function": "vampirism:add_book_nbt"
            }
          ],
          "name": "vampirism:vampire_book"
        },
        {
          "type": "minecraft:empty",
          "weight": 40
        }
      ]
    }
  ]
}
